[{"name":"reinaldi","mobile":"0822459666578","email":"tutu@gmail.com"},{"name":"lelelelelele","mobile":"081230634587","email":"aaa@gmail.com"},{"name":"lala","mobile":"082214575632","email":"lala3@gmail.com"},{"name":"lulu","mobile":"082214572365","email":"lulu@gmail.com"},{"name":"jane do","mobile":"08221415161323","email":"aaa@gmail.com"},{"name":"jane dow","mobile":"081526369655","email":"aaa@gmail.com"},{"name":"jane doww","mobile":"08221415161323","email":"aaa@gmail.com"},{"name":"ffff ","mobile":"08221415161323","email":"f@gmail.com"},{"name":"f","mobile":"081526369655","email":"f@gmail.com"},{"name":"sds","mobile":"08221415161323","email":"aaa@gmail.com"},{"name":"liliaaaa","mobile":"08221415161323","email":"aaa@gmail.com"},{"name":"jane dowwaaaa","mobile":"08221415161323","email":"aaa@gmail.com"}]